README.md
setup.cfg
setup.py
optimiser/__init__.py
optimiser.egg-info/PKG-INFO
optimiser.egg-info/SOURCES.txt
optimiser.egg-info/dependency_links.txt
optimiser.egg-info/requires.txt
optimiser.egg-info/top_level.txt
optimiser/population/__init__.py
optimiser/population/crossentropy.py
optimiser/utils/__init__.py
optimiser/utils/misc.py
tests/__init__.py
tests/population/__init__.py
tests/population/test_crossentropy.py