Metadata-Version: 2.1
Name: optimiser
Version: 0.1.0
Summary: Generic implementations of some numerical optimization methods.
Home-page: https://github.com/Nikolay-Lysenko/optimiser
Author: Nikolay Lysenko
Author-email: nikolay-lysenco@yandex.ru
License: MIT
Keywords: blackbox_optimization,numerical_optimization,crossentropy
Platform: UNKNOWN
Classifier: Development Status :: 3 - Alpha
Classifier: Intended Audience :: Developers
Classifier: Topic :: Scientific/Engineering :: Mathematics
Classifier: License :: OSI Approved :: MIT License
Classifier: Programming Language :: Python :: 3
Requires-Python: >=3.6
